sigpy/__init__.py
sigpy/alg.py
sigpy/app.py
sigpy/backend.py
sigpy/block.py
sigpy/config.py
sigpy/conv.py
sigpy/fourier.py
sigpy/interp.py
sigpy/linop.py
sigpy/plot.py
sigpy/prox.py
sigpy/pytorch.py
sigpy/sim.py
sigpy/thresh.py
sigpy/util.py
sigpy/version.py
sigpy/wavelet.py
sigpy/mri/__init__.py
sigpy/mri/app.py
sigpy/mri/dcf.py
sigpy/mri/linop.py
sigpy/mri/precond.py
sigpy/mri/samp.py
sigpy/mri/sim.py
sigpy/mri/util.py
sigpy/mri/rf/__init__.py
sigpy/mri/rf/adiabatic.py
sigpy/mri/rf/b1sel.py
sigpy/mri/rf/io.py
sigpy/mri/rf/linop.py
sigpy/mri/rf/multiband.py
sigpy/mri/rf/optcont.py
sigpy/mri/rf/ptx.py
sigpy/mri/rf/shim.py
sigpy/mri/rf/sim.py
sigpy/mri/rf/slr.py
sigpy/mri/rf/trajgrad.py
sigpy/mri/rf/util.py
sigpy_lite-0.1.26.dist-info/LICENSE
sigpy_lite-0.1.26.dist-info/METADATA
sigpy_lite-0.1.26.dist-info/WHEEL
sigpy_lite-0.1.26.dist-info/top_level.txt
sigpy_lite-0.1.26.dist-info/RECORD
