Metadata-Version: 2.1
Name: sigpy-lite
Version: 0.1.26
Summary: A light fork of sigpy, a signal processing library for Python.
Author-email: Frank Ong <frankong@berkeley.edu>, Blake Dewey <blake.dewey@jhu.edu>
License: BSD
Project-URL: homepage, https://github.com/blakedewey/sigpy
Project-URL: documentation, https://sigpy.readthedocs.io/en/latest/
Project-URL: repository, https://github.com/blakedewey/sigpy
Classifier: Programming Language :: Python :: 3
Classifier: License :: OSI Approved :: BSD License
Classifier: Operating System :: OS Independent
License-File: LICENSE
Requires-Dist: numpy
Requires-Dist: scipy
Requires-Dist: tqdm
Provides-Extra: full
Requires-Dist: numba ; extra == 'full'
Requires-Dist: pywavelets ; extra == 'full'
Provides-Extra: lint
Requires-Dist: ruff ; extra == 'lint'
Requires-Dist: black ; extra == 'lint'
Requires-Dist: isort ; extra == 'lint'
Requires-Dist: sphinx ; extra == 'lint'
Requires-Dist: sphinx-rtd-theme ; extra == 'lint'
Provides-Extra: test
Requires-Dist: pytest <5.0.0 ; extra == 'test'
Requires-Dist: pytest-cov[all] ; extra == 'test'
Requires-Dist: coverage ; extra == 'test'
